odoo/addons/base_phone/README.rst
odoo/addons/base_phone/__init__.py
odoo/addons/base_phone/__manifest__.py
odoo/addons/base_phone/requirements.txt
odoo/addons/base_phone/i18n/am_ET.po
odoo/addons/base_phone/i18n/ar_001.po
odoo/addons/base_phone/i18n/base_phone.pot
odoo/addons/base_phone/i18n/ca_ES.po
odoo/addons/base_phone/i18n/cs_CZ.po
odoo/addons/base_phone/i18n/de.po
odoo/addons/base_phone/i18n/el_GR.po
odoo/addons/base_phone/i18n/es.po
odoo/addons/base_phone/i18n/es_AR.po
odoo/addons/base_phone/i18n/es_CR.po
odoo/addons/base_phone/i18n/es_EC.po
odoo/addons/base_phone/i18n/es_ES.po
odoo/addons/base_phone/i18n/es_MX.po
odoo/addons/base_phone/i18n/es_VE.po
odoo/addons/base_phone/i18n/et_EE.po
odoo/addons/base_phone/i18n/fi.po
odoo/addons/base_phone/i18n/fr.po
odoo/addons/base_phone/i18n/gl_ES.po
odoo/addons/base_phone/i18n/hr.po
odoo/addons/base_phone/i18n/it.po
odoo/addons/base_phone/i18n/lt.po
odoo/addons/base_phone/i18n/nl.po
odoo/addons/base_phone/i18n/nl_BE.po
odoo/addons/base_phone/i18n/pl.po
odoo/addons/base_phone/i18n/pt.po
odoo/addons/base_phone/i18n/pt_BR.po
odoo/addons/base_phone/i18n/pt_PT.po
odoo/addons/base_phone/i18n/ro.po
odoo/addons/base_phone/i18n/ru.po
odoo/addons/base_phone/i18n/sl_SI.po
odoo/addons/base_phone/i18n/th.po
odoo/addons/base_phone/i18n/tr.po
odoo/addons/base_phone/i18n/vi_VN.po
odoo/addons/base_phone/models/__init__.py
odoo/addons/base_phone/models/ir_fields_converter.py
odoo/addons/base_phone/models/phone_common.py
odoo/addons/base_phone/models/phone_validation_mixin.py
odoo/addons/base_phone/models/res_company.py
odoo/addons/base_phone/models/res_partner.py
odoo/addons/base_phone/readme/CONTRIBUTORS.md
odoo/addons/base_phone/readme/DESCRIPTION.md
odoo/addons/base_phone/security/ir.model.access.csv
odoo/addons/base_phone/security/phone_security.xml
odoo/addons/base_phone/static/description/icon.png
odoo/addons/base_phone/static/description/index.html
odoo_addon_base_phone-18.0.1.0.0.8.dist-info/METADATA
odoo_addon_base_phone-18.0.1.0.0.8.dist-info/WHEEL
odoo_addon_base_phone-18.0.1.0.0.8.dist-info/top_level.txt
odoo_addon_base_phone-18.0.1.0.0.8.dist-info/RECORD
