Metadata-Version: 2.1
Name: odoo-addon-base_phone
Version: 18.0.1.0.0.8
Requires-Python: >=3.10
Requires-Dist: odoo==18.0.*
Requires-Dist: phonenumbers
Summary: Validate phone numbers
Home-page: https://github.com/OCA/connector-telephony
License: AGPL-3
Author: Akretion,Odoo Community Association (OCA)
Author-email: support@odoo-community.org
Classifier: Programming Language :: Python
Classifier: Framework :: Odoo
Classifier: Framework :: Odoo :: 18.0
Classifier: License :: OSI Approved :: GNU Affero General Public License v3
